eztools/__init__.py
eztools/config.py
eztools/converters.py
eztools/decorators.py
eztools/fileops.py
eztools/formatters.py
eztools/logger.py
eztools/string_utils.py
eztools-0.1.1.dist-info/LICENSE
eztools-0.1.1.dist-info/METADATA
eztools-0.1.1.dist-info/WHEEL
eztools-0.1.1.dist-info/top_level.txt
eztools-0.1.1.dist-info/RECORD
